{
  "contributions": [
    {
      "_id": "1775201789829",
      "name": "Rohit G",
      "amount": 2000,
      "date": "2026-04-03T07:36:29.829Z"
    },
    {
      "_id": "1775204828732",
      "name": "Tushar G",
      "amount": 2000,
      "date": "2026-04-03T08:27:08.732Z"
    },
    {
      "_id": "1775205489357",
      "name": "Akash M",
      "amount": 2000,
      "date": "2026-04-03T08:38:09.357Z"
    },
    {
      "_id": "1775206107342",
      "name": "KD",
      "amount": 2000,
      "date": "2026-04-03T08:48:27.342Z"
    }
  ],
  "expenses": [
    {
      "_id": "1775201804077",
      "name": "Food",
      "amount": 1500,
      "paidBy": "Unknown",
      "date": "2026-04-03T07:36:44.077Z"
    },
    {
      "_id": "1775205471489",
      "name": "Travel",
      "amount": 500,
      "paidBy": "Unknown",
      "date": "2026-04-03T08:37:51.489Z"
    }
  ]
}